dispand/__init__.py
dispand/dispand.py
dispand-1.0.0.dist-info/LICENSE
dispand-1.0.0.dist-info/METADATA
dispand-1.0.0.dist-info/WHEEL
dispand-1.0.0.dist-info/top_level.txt
dispand-1.0.0.dist-info/RECORD
