Metadata-Version: 2.1
Name: dispand
Version: 1.0.0
Summary: expand discord message links
Home-page: https://github.com/peco2282/expander
Author: peco2282
Author-email: pecop2282@gmail.com
License: MIT
License-File: LICENSE
Requires-Dist: py-cord (>=2.0.0b1)
